my_pypi_custom_package_1/__init__.py
my_pypi_custom_package_1/basic/__init__.py
my_pypi_custom_package_1/basic/hello_world.py
my_pypi_custom_package_1/basic/hello_world_2.py
my_pypi_custom_package_1/basic/algebra/__init__.py
my_pypi_custom_package_1/basic/algebra/addition.py
my_pypi_custom_package_1/basic/algebra/subraction.py
my_pypi_custom_package_1/basic/custom_utils/__init__.py
my_pypi_custom_package_1/basic/custom_utils/today_date.py
my_pypi_custom_package_1/sorting/__init__.py
my_pypi_custom_package_1/sorting/sorted_list.py
my_pypi_custom_package_2/__init__.py
my_pypi_custom_package_2/basic/__init__.py
my_pypi_custom_package_2/basic/hello_world.py
my_pypi_custom_package_2/basic/hello_world_2.py
my_pypi_custom_package_2/basic/algebra/__init__.py
my_pypi_custom_package_2/basic/algebra/addition.py
my_pypi_custom_package_2/basic/algebra/multiplication.py
my_pypi_custom_package_2/basic/algebra/subraction.py
my_pypi_custom_package_2/basic/custom_utils/__init__.py
my_pypi_custom_package_2/basic/custom_utils/today_date.py
my_pypi_custom_package_2/sorting/__init__.py
my_pypi_custom_package_2/sorting/sorted_list.py
my_pypi_custom_package-0.0.29.dist-info/METADATA
my_pypi_custom_package-0.0.29.dist-info/WHEEL
my_pypi_custom_package-0.0.29.dist-info/top_level.txt
my_pypi_custom_package-0.0.29.dist-info/RECORD
